setup.py
salure_helpers/shiftbase/__init__.py
salure_helpers/shiftbase/shiftbase.py
salure_helpers_shiftbase.egg-info/PKG-INFO
salure_helpers_shiftbase.egg-info/SOURCES.txt
salure_helpers_shiftbase.egg-info/dependency_links.txt
salure_helpers_shiftbase.egg-info/not-zip-safe
salure_helpers_shiftbase.egg-info/requires.txt
salure_helpers_shiftbase.egg-info/top_level.txt